aioarango/__init__.py
aioarango/api.py
aioarango/aql.py
aioarango/backup.py
aioarango/client.py
aioarango/cluster.py
aioarango/collection.py
aioarango/connection.py
aioarango/cursor.py
aioarango/database.py
aioarango/errno.py
aioarango/exceptions.py
aioarango/executor.py
aioarango/formatter.py
aioarango/foxx.py
aioarango/graph.py
aioarango/http.py
aioarango/job.py
aioarango/pregel.py
aioarango/replication.py
aioarango/request.py
aioarango/resolver.py
aioarango/response.py
aioarango/result.py
aioarango/typings.py
aioarango/utils.py
aioarango/version.py
aioarango/wal.py
aioarango-1.0.0.dist-info/LICENSE
aioarango-1.0.0.dist-info/WHEEL
aioarango-1.0.0.dist-info/METADATA
aioarango-1.0.0.dist-info/RECORD
