Metadata-Version: 2.1
Name: aioarango
Version: 1.0.0
Summary: Asynchronous driver for ArangoDB
Home-page: https://github.com/mirrorrim/aioarango
License: MIT
Author: Alexey Tylindus
Author-email: a.tylindus@gmail.com
Requires-Python: >=3.7,<4.0
Classifier: Intended Audience :: Developers
Classifier: License :: OSI Approved :: MIT License
Classifier: Natural Language :: English
Classifier: Operating System :: MacOS
Classifier: Operating System :: Microsoft :: Windows
Classifier: Operating System :: Unix
Classifier: Programming Language :: Python :: 3
Classifier: Programming Language :: Python :: 3.7
Classifier: Programming Language :: Python :: 3.8
Classifier: Programming Language :: Python :: 3.9
Classifier: Topic :: Documentation :: Sphinx
Requires-Dist: PyJWT (>=2.1.0,<3.0.0)
Requires-Dist: httpx (>=0.18.2,<0.19.0)
Requires-Dist: requests-toolbelt (>=0.9.1,<0.10.0)
Project-URL: Repository, https://github.com/mirrorrim/aioarango
